{
  "data_dir": "data\\test_dataset\\bias",
  "split_name": "bias",
  "results": [
    {
      "label": "ppo-seed42",
      "baseline_name": "ppo-seed42",
      "scenario": "bias",
      "seed": 42,
      "model_path": "runs\\ppo\\runs\\bias\\seed42\\checkpoints\\best_model.zip",
      "data_dir": "data\\test_dataset\\bias",
      "n_eval_episodes": 50,
      "mean_reward": -6334.421599370241,
      "std_reward": 7462.138066575003,
      "min_reward": -35210.47006547451,
      "max_reward": -45.0,
      "mean_ep_length": 303.84,
      "std_ep_length": 105.84845015398194,
      "mean_waiting_time": 16.906996492147446,
      "std_waiting_time": 16.239479740522505,
      "mean_p95_waiting_time": 76.38683357715607,
      "mean_max_waiting_time": 94.22896278381347,
      "dataset_total_waiting_time": 316721.08017005026,
      "dataset_vehicle_count": 15192,
      "dataset_average_waiting_time": 20.847885740524635,
      "mean_cv_load_imbalance": 0.47637541520181886,
      "invalid_action_rate": 0.0,
      "invalid_action_count": 0,
      "decision_step_count": 15192,
      "episode_rewards": [
        -21349.45233154297,
        -12423.146244049072,
        -16616.426978960633,
        -252.0,
        -3619.9572482705116,
        -6192.872064590454,
        -45.0,
        -9390.568572998047,
        -3911.099998474121,
        -3820.150002479553,
        -350.0,
        -3244.0,
        -266.0,
        -3415.0,
        -4273.336946487427,
        -2088.0,
        -1432.0,
        -343.0,
        -15576.91916179657,
        -6097.398693680763,
        -5254.929128944874,
        -19182.369534134865,
        -13283.640763282776,
        -35210.47006547451,
        -82.0,
        -311.0,
        -15253.624450683594,
        -8420.446385860443,
        -20120.38072104752,
        -20848.461508512497,
        -6348.431079864502,
        -913.1999969482422,
        -4509.850520610809,
        -9572.091544151306,
        -681.0,
        -584.1499994397163,
        -215.0,
        -103.79999995231628,
        -9116.0,
        -4873.683004975319,
        -2464.1577347815037,
        -1541.799994468689,
        -517.6499999761581,
        -913.0,
        -4815.0,
        -12110.915291786194,
        -1058.0,
        -77.0,
        -288.0,
        -3344.7000002861023
      ],
      "episode_lengths": [
        436,
        301,
        384,
        224,
        304,
        204,
        116,
        469,
        265,
        388,
        146,
        269,
        126,
        240,
        357,
        272,
        240,
        191,
        352,
        282,
        270,
        453,
        429,
        528,
        195,
        192,
        422,
        243,
        516,
        514,
        409,
        135,
        344,
        310,
        291,
        327,
        208,
        225,
        351,
        410,
        356,
        280,
        207,
        218,
        304,
        441,
        257,
        272,
        145,
        374
      ],
      "episode_names": [
        "episode_0000.csv",
        "episode_0001.csv",
        "episode_0002.csv",
        "episode_0003.csv",
        "episode_0004.csv",
        "episode_0005.csv",
        "episode_0006.csv",
        "episode_0007.csv",
        "episode_0008.csv",
        "episode_0009.csv",
        "episode_0010.csv",
        "episode_0011.csv",
        "episode_0012.csv",
        "episode_0013.csv",
        "episode_0014.csv",
        "episode_0015.csv",
        "episode_0016.csv",
        "episode_0017.csv",
        "episode_0018.csv",
        "episode_0019.csv",
        "episode_0020.csv",
        "episode_0021.csv",
        "episode_0022.csv",
        "episode_0023.csv",
        "episode_0024.csv",
        "episode_0025.csv",
        "episode_0026.csv",
        "episode_0027.csv",
        "episode_0028.csv",
        "episode_0029.csv",
        "episode_0030.csv",
        "episode_0031.csv",
        "episode_0032.csv",
        "episode_0033.csv",
        "episode_0034.csv",
        "episode_0035.csv",
        "episode_0036.csv",
        "episode_0037.csv",
        "episode_0038.csv",
        "episode_0039.csv",
        "episode_0040.csv",
        "episode_0041.csv",
        "episode_0042.csv",
        "episode_0043.csv",
        "episode_0044.csv",
        "episode_0045.csv",
        "episode_0046.csv",
        "episode_0047.csv",
        "episode_0048.csv",
        "episode_0049.csv"
      ],
      "episode_metrics": [
        {
          "episode_name": "episode_0000.csv",
          "episode_reward": -21349.45233154297,
          "episode_length": 436,
          "vehicle_count": 436,
          "total_waiting_time": 21349.45241355896,
          "mean_waiting_time": 48.966636657714844,
          "p95_waiting_time": 117.0491714477539,
          "max_waiting_time": 130.588623046875,
          "cv_load_imbalance": 0.32931115232226743,
          "assigned_demand_by_station": [
            2028.7499999999998,
            3773.95,
            3917.5499999999993,
            2652.2000000000007,
            1860.2499999999998,
            1269.3000000000002,
            2406.999999999999
          ],
          "normalized_assigned_demand_by_station": [
            202.87499999999997,
            150.958,
            217.64166666666662,
            221.01666666666674,
            155.02083333333331,
            57.69545454545455,
            133.72222222222217
          ]
        },
        {
          "episode_name": "episode_0001.csv",
          "episode_reward": -12423.146244049072,
          "episode_length": 301,
          "vehicle_count": 301,
          "total_waiting_time": 12423.146236419678,
          "mean_waiting_time": 41.272911071777344,
          "p95_waiting_time": 193.0,
          "max_waiting_time": 203.0,
          "cv_load_imbalance": 0.6657158162001965,
          "assigned_demand_by_station": [
            3151.6,
            907.0,
            1035.5,
            1300.0,
            1904.2,
            2556.4,
            1828.3
          ],
          "normalized_assigned_demand_by_station": [
            315.15999999999997,
            36.28,
            57.52777777777778,
            108.33333333333333,
            158.68333333333334,
            116.2,
            101.57222222222222
          ]
        },
        {
          "episode_name": "episode_0002.csv",
          "episode_reward": -16616.426978960633,
          "episode_length": 384,
          "vehicle_count": 384,
          "total_waiting_time": 16616.426961794496,
          "mean_waiting_time": 43.271942138671875,
          "p95_waiting_time": 196.75999450683594,
          "max_waiting_time": 226.39999389648438,
          "cv_load_imbalance": 0.6745219004856291,
          "assigned_demand_by_station": [
            3802.25,
            1010.7,
            1333.3999999999999,
            1144.7000000000003,
            1800.4999999999998,
            3982.0999999999995,
            2709.35
          ],
          "normalized_assigned_demand_by_station": [
            380.225,
            40.428000000000004,
            74.07777777777777,
            95.3916666666667,
            150.04166666666666,
            181.00454545454542,
            150.51944444444445
          ]
        },
        {
          "episode_name": "episode_0003.csv",
          "episode_reward": -252.0,
          "episode_length": 224,
          "vehicle_count": 224,
          "total_waiting_time": 252.0,
          "mean_waiting_time": 1.125,
          "p95_waiting_time": 10.550000190734863,
          "max_waiting_time": 23.0,
          "cv_load_imbalance": 0.30202480661094333,
          "assigned_demand_by_station": [
            1285.0,
            1882.0,
            1043.0,
            1193.0,
            1403.0,
            1334.0,
            1228.0
          ],
          "normalized_assigned_demand_by_station": [
            128.5,
            75.28,
            57.94444444444444,
            99.41666666666667,
            116.91666666666667,
            60.63636363636363,
            68.22222222222223
          ]
        },
        {
          "episode_name": "episode_0004.csv",
          "episode_reward": -3619.9572482705116,
          "episode_length": 304,
          "vehicle_count": 304,
          "total_waiting_time": 3619.9572482705116,
          "mean_waiting_time": 11.907753944396973,
          "p95_waiting_time": 49.0,
          "max_waiting_time": 69.0,
          "cv_load_imbalance": 0.3036894218354641,
          "assigned_demand_by_station": [
            1718.6000000000001,
            1848.65,
            1684.8,
            1763.0,
            1754.75,
            1917.7999999999997,
            1652.3999999999999
          ],
          "normalized_assigned_demand_by_station": [
            171.86,
            73.946,
            93.6,
            146.91666666666666,
            146.22916666666666,
            87.17272727272726,
            91.8
          ]
        },
        {
          "episode_name": "episode_0005.csv",
          "episode_reward": -6192.872064590454,
          "episode_length": 204,
          "vehicle_count": 204,
          "total_waiting_time": 6192.872064590454,
          "mean_waiting_time": 30.357215881347656,
          "p95_waiting_time": 139.0,
          "max_waiting_time": 148.8000030517578,
          "cv_load_imbalance": 0.8772668142968122,
          "assigned_demand_by_station": [
            2338.9500000000003,
            1897.7999999999997,
            859.95,
            288.3,
            404.65,
            730.7,
            1690.65
          ],
          "normalized_assigned_demand_by_station": [
            233.89500000000004,
            75.91199999999999,
            47.775000000000006,
            24.025000000000002,
            33.72083333333333,
            33.21363636363637,
            93.92500000000001
          ]
        },
        {
          "episode_name": "episode_0006.csv",
          "episode_reward": -45.0,
          "episode_length": 116,
          "vehicle_count": 116,
          "total_waiting_time": 45.0,
          "mean_waiting_time": 0.38793104887008667,
          "p95_waiting_time": 0.0,
          "max_waiting_time": 14.0,
          "cv_load_imbalance": 0.4172078673121232,
          "assigned_demand_by_station": [
            600.0,
            477.0,
            560.0,
            908.0,
            792.0,
            677.0,
            794.0
          ],
          "normalized_assigned_demand_by_station": [
            60.0,
            19.08,
            31.11111111111111,
            75.66666666666667,
            66.0,
            30.772727272727273,
            44.111111111111114
          ]
        },
        {
          "episode_name": "episode_0007.csv",
          "episode_reward": -9390.568572998047,
          "episode_length": 469,
          "vehicle_count": 469,
          "total_waiting_time": 9390.568572998047,
          "mean_waiting_time": 20.022533416748047,
          "p95_waiting_time": 115.19999694824219,
          "max_waiting_time": 144.0,
          "cv_load_imbalance": 0.357205698074506,
          "assigned_demand_by_station": [
            2601.0,
            2657.5,
            1936.5,
            2140.9,
            1823.3999999999999,
            2256.3999999999996,
            2263.3
          ],
          "normalized_assigned_demand_by_station": [
            260.1,
            106.3,
            107.58333333333333,
            178.40833333333333,
            151.95,
            102.56363636363635,
            125.7388888888889
          ]
        },
        {
          "episode_name": "episode_0008.csv",
          "episode_reward": -3911.099998474121,
          "episode_length": 265,
          "vehicle_count": 265,
          "total_waiting_time": 3911.099998474121,
          "mean_waiting_time": 14.758868217468262,
          "p95_waiting_time": 49.0,
          "max_waiting_time": 74.0,
          "cv_load_imbalance": 0.24615483604860453,
          "assigned_demand_by_station": [
            1338.8,
            1387.0,
            1729.0,
            1401.0,
            1137.0,
            1714.7,
            2041.5
          ],
          "normalized_assigned_demand_by_station": [
            133.88,
            55.48,
            96.05555555555556,
            116.75,
            94.75,
            77.94090909090909,
            113.41666666666667
          ]
        },
        {
          "episode_name": "episode_0009.csv",
          "episode_reward": -3820.150002479553,
          "episode_length": 388,
          "vehicle_count": 388,
          "total_waiting_time": 3820.150002479553,
          "mean_waiting_time": 9.845746994018555,
          "p95_waiting_time": 64.6500015258789,
          "max_waiting_time": 81.80000305175781,
          "cv_load_imbalance": 0.4432034496477147,
          "assigned_demand_by_station": [
            1852.8,
            1829.05,
            1148.0,
            1134.95,
            1304.0,
            1545.8000000000002,
            1004.4
          ],
          "normalized_assigned_demand_by_station": [
            185.28,
            73.16199999999999,
            63.77777777777778,
            94.57916666666667,
            108.66666666666667,
            70.26363636363637,
            55.8
          ]
        },
        {
          "episode_name": "episode_0010.csv",
          "episode_reward": -350.0,
          "episode_length": 146,
          "vehicle_count": 146,
          "total_waiting_time": 350.0,
          "mean_waiting_time": 2.3972601890563965,
          "p95_waiting_time": 20.0,
          "max_waiting_time": 28.0,
          "cv_load_imbalance": 0.7848387193559607,
          "assigned_demand_by_station": [
            1095.0,
            203.5,
            286.0,
            481.0,
            330.0,
            732.0,
            719.5
          ],
          "normalized_assigned_demand_by_station": [
            109.5,
            8.14,
            15.88888888888889,
            40.083333333333336,
            27.5,
            33.27272727272727,
            39.97222222222222
          ]
        },
        {
          "episode_name": "episode_0011.csv",
          "episode_reward": -3244.0,
          "episode_length": 269,
          "vehicle_count": 269,
          "total_waiting_time": 3244.0,
          "mean_waiting_time": 12.059479713439941,
          "p95_waiting_time": 56.599998474121094,
          "max_waiting_time": 71.0,
          "cv_load_imbalance": 0.40461895160884626,
          "assigned_demand_by_station": [
            1387.0,
            951.0,
            1411.0,
            1471.0,
            1072.0,
            933.0,
            1616.0
          ],
          "normalized_assigned_demand_by_station": [
            138.7,
            38.04,
            78.38888888888889,
            122.58333333333333,
            89.33333333333333,
            42.40909090909091,
            89.77777777777777
          ]
        },
        {
          "episode_name": "episode_0012.csv",
          "episode_reward": -266.0,
          "episode_length": 126,
          "vehicle_count": 126,
          "total_waiting_time": 266.0,
          "mean_waiting_time": 2.1111111640930176,
          "p95_waiting_time": 18.0,
          "max_waiting_time": 42.0,
          "cv_load_imbalance": 0.5430144219899281,
          "assigned_demand_by_station": [
            1002.0,
            706.0,
            578.0,
            990.0,
            530.0,
            819.0,
            461.0
          ],
          "normalized_assigned_demand_by_station": [
            100.2,
            28.24,
            32.111111111111114,
            82.5,
            44.166666666666664,
            37.22727272727273,
            25.61111111111111
          ]
        },
        {
          "episode_name": "episode_0013.csv",
          "episode_reward": -3415.0,
          "episode_length": 240,
          "vehicle_count": 240,
          "total_waiting_time": 3415.0,
          "mean_waiting_time": 14.229166984558105,
          "p95_waiting_time": 92.0,
          "max_waiting_time": 102.0,
          "cv_load_imbalance": 0.7376465167030635,
          "assigned_demand_by_station": [
            2642.0,
            784.0,
            760.0,
            1019.0,
            983.0,
            1580.0,
            1939.0
          ],
          "normalized_assigned_demand_by_station": [
            264.2,
            31.36,
            42.22222222222222,
            84.91666666666667,
            81.91666666666667,
            71.81818181818181,
            107.72222222222223
          ]
        },
        {
          "episode_name": "episode_0014.csv",
          "episode_reward": -4273.336946487427,
          "episode_length": 357,
          "vehicle_count": 357,
          "total_waiting_time": 4273.336947262287,
          "mean_waiting_time": 11.970131874084473,
          "p95_waiting_time": 80.0,
          "max_waiting_time": 112.0,
          "cv_load_imbalance": 0.3374975211895041,
          "assigned_demand_by_station": [
            1932.4999999999998,
            2321.5,
            1626.4,
            1269.0500000000002,
            1032.0,
            1876.9000000000003,
            1658.65
          ],
          "normalized_assigned_demand_by_station": [
            193.24999999999997,
            92.86,
            90.35555555555555,
            105.75416666666668,
            86.0,
            85.31363636363638,
            92.14722222222223
          ]
        },
        {
          "episode_name": "episode_0015.csv",
          "episode_reward": -2088.0,
          "episode_length": 272,
          "vehicle_count": 272,
          "total_waiting_time": 2088.0,
          "mean_waiting_time": 7.676470756530762,
          "p95_waiting_time": 30.450000762939453,
          "max_waiting_time": 52.0,
          "cv_load_imbalance": 0.32731507678032745,
          "assigned_demand_by_station": [
            1335.0,
            1425.0,
            1233.0,
            1223.0,
            1091.0,
            1686.0,
            871.0
          ],
          "normalized_assigned_demand_by_station": [
            133.5,
            57.0,
            68.5,
            101.91666666666667,
            90.91666666666667,
            76.63636363636364,
            48.388888888888886
          ]
        },
        {
          "episode_name": "episode_0016.csv",
          "episode_reward": -1432.0,
          "episode_length": 240,
          "vehicle_count": 240,
          "total_waiting_time": 1432.0,
          "mean_waiting_time": 5.9666666984558105,
          "p95_waiting_time": 42.04999923706055,
          "max_waiting_time": 54.0,
          "cv_load_imbalance": 0.571905224772341,
          "assigned_demand_by_station": [
            1834.0,
            910.0,
            799.0,
            749.0,
            1028.0,
            1636.0,
            1224.0
          ],
          "normalized_assigned_demand_by_station": [
            183.4,
            36.4,
            44.388888888888886,
            62.416666666666664,
            85.66666666666667,
            74.36363636363636,
            68.0
          ]
        },
        {
          "episode_name": "episode_0017.csv",
          "episode_reward": -343.0,
          "episode_length": 191,
          "vehicle_count": 191,
          "total_waiting_time": 343.0,
          "mean_waiting_time": 1.7958115339279175,
          "p95_waiting_time": 10.0,
          "max_waiting_time": 15.0,
          "cv_load_imbalance": 0.34566504592898223,
          "assigned_demand_by_station": [
            674.0,
            813.0,
            750.0,
            600.0,
            774.0,
            896.0,
            361.0
          ],
          "normalized_assigned_demand_by_station": [
            67.4,
            32.52,
            41.666666666666664,
            50.0,
            64.5,
            40.72727272727273,
            20.055555555555557
          ]
        },
        {
          "episode_name": "episode_0018.csv",
          "episode_reward": -15576.91916179657,
          "episode_length": 352,
          "vehicle_count": 352,
          "total_waiting_time": 15576.919172286987,
          "mean_waiting_time": 44.25260925292969,
          "p95_waiting_time": 196.35000610351562,
          "max_waiting_time": 221.0,
          "cv_load_imbalance": 0.7212082136439407,
          "assigned_demand_by_station": [
            3071.0999999999995,
            884.2,
            890.5,
            1147.4499999999998,
            1213.6499999999999,
            2034.4000000000003,
            2328.7000000000007
          ],
          "normalized_assigned_demand_by_station": [
            307.10999999999996,
            35.368,
            49.47222222222222,
            95.62083333333332,
            101.13749999999999,
            92.47272727272728,
            129.37222222222226
          ]
        },
        {
          "episode_name": "episode_0019.csv",
          "episode_reward": -6097.398693680763,
          "episode_length": 282,
          "vehicle_count": 282,
          "total_waiting_time": 6097.39868414402,
          "mean_waiting_time": 21.621980667114258,
          "p95_waiting_time": 103.56999969482422,
          "max_waiting_time": 125.80000305175781,
          "cv_load_imbalance": 0.5223394757022817,
          "assigned_demand_by_station": [
            2008.2499999999993,
            1160.2500000000007,
            1381.5,
            893.4499999999999,
            1164.75,
            1388.5500000000006,
            1338.2500000000002
          ],
          "normalized_assigned_demand_by_station": [
            200.82499999999993,
            46.410000000000025,
            76.75,
            74.45416666666667,
            97.0625,
            63.11590909090912,
            74.34722222222223
          ]
        },
        {
          "episode_name": "episode_0020.csv",
          "episode_reward": -5254.929128944874,
          "episode_length": 270,
          "vehicle_count": 270,
          "total_waiting_time": 5254.929121792316,
          "mean_waiting_time": 19.462697982788086,
          "p95_waiting_time": 86.7125015258789,
          "max_waiting_time": 91.25,
          "cv_load_imbalance": 0.7172901077410346,
          "assigned_demand_by_station": [
            2577.6000000000004,
            2401.9999999999995,
            845.7999999999998,
            439.3,
            567.7,
            1809.9000000000003,
            2345.7
          ],
          "normalized_assigned_demand_by_station": [
            257.76000000000005,
            96.07999999999998,
            46.98888888888888,
            36.608333333333334,
            47.30833333333334,
            82.26818181818183,
            130.31666666666666
          ]
        },
        {
          "episode_name": "episode_0021.csv",
          "episode_reward": -19182.369534134865,
          "episode_length": 453,
          "vehicle_count": 453,
          "total_waiting_time": 19182.369495749474,
          "mean_waiting_time": 42.345184326171875,
          "p95_waiting_time": 171.6999969482422,
          "max_waiting_time": 185.4499969482422,
          "cv_load_imbalance": 0.6828635955110729,
          "assigned_demand_by_station": [
            3285.4500000000016,
            2884.8499999999995,
            1322.4999999999998,
            848.75,
            897.1,
            1621.9999999999998,
            4184.349999999999
          ],
          "normalized_assigned_demand_by_station": [
            328.5450000000002,
            115.39399999999998,
            73.47222222222221,
            70.72916666666667,
            74.75833333333334,
            73.72727272727272,
            232.46388888888885
          ]
        },
        {
          "episode_name": "episode_0022.csv",
          "episode_reward": -13283.640763282776,
          "episode_length": 429,
          "vehicle_count": 429,
          "total_waiting_time": 13283.640789985657,
          "mean_waiting_time": 30.964197158813477,
          "p95_waiting_time": 104.62999725341797,
          "max_waiting_time": 145.5500030517578,
          "cv_load_imbalance": 0.3086364293589082,
          "assigned_demand_by_station": [
            2171.4999999999995,
            2194.0,
            1990.0000000000007,
            1393.85,
            1797.9999999999995,
            2140.4500000000016,
            2573.199999999999
          ],
          "normalized_assigned_demand_by_station": [
            217.14999999999995,
            87.76,
            110.5555555555556,
            116.15416666666665,
            149.8333333333333,
            97.29318181818189,
            142.9555555555555
          ]
        },
        {
          "episode_name": "episode_0023.csv",
          "episode_reward": -35210.47006547451,
          "episode_length": 528,
          "vehicle_count": 528,
          "total_waiting_time": 35210.47017157078,
          "mean_waiting_time": 66.68649291992188,
          "p95_waiting_time": 275.74749755859375,
          "max_waiting_time": 297.25,
          "cv_load_imbalance": 0.648156732914983,
          "assigned_demand_by_station": [
            5100.799999999999,
            2109.7,
            1667.3500000000001,
            1674.1000000000001,
            2214.2499999999995,
            4023.7000000000016,
            5475.1
          ],
          "normalized_assigned_demand_by_station": [
            510.0799999999999,
            84.38799999999999,
            92.63055555555556,
            139.50833333333335,
            184.5208333333333,
            182.8954545454546,
            304.1722222222222
          ]
        },
        {
          "episode_name": "episode_0024.csv",
          "episode_reward": -82.0,
          "episode_length": 195,
          "vehicle_count": 195,
          "total_waiting_time": 82.0,
          "mean_waiting_time": 0.4205128252506256,
          "p95_waiting_time": 3.299999952316284,
          "max_waiting_time": 12.0,
          "cv_load_imbalance": 0.2719093930942652,
          "assigned_demand_by_station": [
            624.0,
            864.0,
            876.0,
            1003.0,
            771.0,
            1009.0,
            836.0
          ],
          "normalized_assigned_demand_by_station": [
            62.4,
            34.56,
            48.666666666666664,
            83.58333333333333,
            64.25,
            45.86363636363637,
            46.44444444444444
          ]
        },
        {
          "episode_name": "episode_0025.csv",
          "episode_reward": -311.0,
          "episode_length": 192,
          "vehicle_count": 192,
          "total_waiting_time": 311.0,
          "mean_waiting_time": 1.6197916269302368,
          "p95_waiting_time": 11.449999809265137,
          "max_waiting_time": 34.0,
          "cv_load_imbalance": 0.33799308600803896,
          "assigned_demand_by_station": [
            876.0,
            1462.0,
            624.0,
            987.0,
            743.0,
            1305.0,
            540.0
          ],
          "normalized_assigned_demand_by_station": [
            87.6,
            58.48,
            34.666666666666664,
            82.25,
            61.916666666666664,
            59.31818181818182,
            30.0
          ]
        },
        {
          "episode_name": "episode_0026.csv",
          "episode_reward": -15253.624450683594,
          "episode_length": 422,
          "vehicle_count": 422,
          "total_waiting_time": 15253.624450683594,
          "mean_waiting_time": 36.14603042602539,
          "p95_waiting_time": 191.85000610351562,
          "max_waiting_time": 245.0,
          "cv_load_imbalance": 0.6679341050016938,
          "assigned_demand_by_station": [
            3288.4,
            1465.5,
            1149.7,
            878.1999999999999,
            1499.15,
            2356.7499999999986,
            2922.3000000000006
          ],
          "normalized_assigned_demand_by_station": [
            328.84000000000003,
            58.62,
            63.87222222222223,
            73.18333333333332,
            124.92916666666667,
            107.12499999999994,
            162.35000000000002
          ]
        },
        {
          "episode_name": "episode_0027.csv",
          "episode_reward": -8420.446385860443,
          "episode_length": 243,
          "vehicle_count": 243,
          "total_waiting_time": 8420.44638967514,
          "mean_waiting_time": 34.652042388916016,
          "p95_waiting_time": 168.9199981689453,
          "max_waiting_time": 177.39999389648438,
          "cv_load_imbalance": 0.8918240999135698,
          "assigned_demand_by_station": [
            3000.4000000000005,
            2349.0000000000005,
            669.8000000000001,
            371.25,
            691.0,
            1309.3999999999996,
            1766.15
          ],
          "normalized_assigned_demand_by_station": [
            300.0400000000001,
            93.96000000000002,
            37.211111111111116,
            30.9375,
            57.583333333333336,
            59.5181818181818,
            98.11944444444445
          ]
        },
        {
          "episode_name": "episode_0028.csv",
          "episode_reward": -20120.38072104752,
          "episode_length": 516,
          "vehicle_count": 516,
          "total_waiting_time": 20120.38073515892,
          "mean_waiting_time": 38.992984771728516,
          "p95_waiting_time": 142.75,
          "max_waiting_time": 194.5,
          "cv_load_imbalance": 0.4089998613956742,
          "assigned_demand_by_station": [
            3738.1,
            4029.2000000000003,
            2083.8999999999996,
            3149.2,
            3155.8,
            2836.2,
            3039.6000000000004
          ],
          "normalized_assigned_demand_by_station": [
            373.81,
            161.168,
            115.7722222222222,
            262.43333333333334,
            262.98333333333335,
            128.9181818181818,
            168.86666666666667
          ]
        },
        {
          "episode_name": "episode_0029.csv",
          "episode_reward": -20848.461508512497,
          "episode_length": 514,
          "vehicle_count": 514,
          "total_waiting_time": 20848.461517333984,
          "mean_waiting_time": 40.56120681762695,
          "p95_waiting_time": 188.15509033203125,
          "max_waiting_time": 228.0,
          "cv_load_imbalance": 0.5195033932222279,
          "assigned_demand_by_station": [
            3435.8,
            2625.5,
            1757.2499999999998,
            1912.5500000000002,
            2223.2000000000003,
            1796.5000000000005,
            2529.2
          ],
          "normalized_assigned_demand_by_station": [
            343.58000000000004,
            105.02,
            97.62499999999999,
            159.3791666666667,
            185.26666666666668,
            81.65909090909093,
            140.5111111111111
          ]
        },
        {
          "episode_name": "episode_0030.csv",
          "episode_reward": -6348.431079864502,
          "episode_length": 409,
          "vehicle_count": 409,
          "total_waiting_time": 6348.431079864502,
          "mean_waiting_time": 15.521835327148438,
          "p95_waiting_time": 85.0,
          "max_waiting_time": 109.0,
          "cv_load_imbalance": 0.4200884893130767,
          "assigned_demand_by_station": [
            2457.0,
            1991.1999999999998,
            1971.0,
            1364.0,
            1824.8,
            1811.4,
            1899.6000000000001
          ],
          "normalized_assigned_demand_by_station": [
            245.7,
            79.648,
            109.5,
            113.66666666666667,
            152.06666666666666,
            82.33636363636364,
            105.53333333333335
          ]
        },
        {
          "episode_name": "episode_0031.csv",
          "episode_reward": -913.1999969482422,
          "episode_length": 135,
          "vehicle_count": 135,
          "total_waiting_time": 913.1999969482422,
          "mean_waiting_time": 6.764444351196289,
          "p95_waiting_time": 40.599998474121094,
          "max_waiting_time": 50.0,
          "cv_load_imbalance": 0.8171987975581868,
          "assigned_demand_by_station": [
            1482.1999999999998,
            1763.8,
            657.0,
            521.0,
            186.0,
            757.0,
            310.0
          ],
          "normalized_assigned_demand_by_station": [
            148.21999999999997,
            70.55199999999999,
            36.5,
            43.416666666666664,
            15.5,
            34.40909090909091,
            17.22222222222222
          ]
        },
        {
          "episode_name": "episode_0032.csv",
          "episode_reward": -4509.850520610809,
          "episode_length": 344,
          "vehicle_count": 344,
          "total_waiting_time": 4509.850515604019,
          "mean_waiting_time": 13.110031127929688,
          "p95_waiting_time": 39.58222961425781,
          "max_waiting_time": 53.90951919555664,
          "cv_load_imbalance": 0.33578922976066466,
          "assigned_demand_by_station": [
            899.9,
            2426.5000000000005,
            2434.4,
            1715.3999999999996,
            1636.7,
            972.0000000000001,
            1312.0999999999995
          ],
          "normalized_assigned_demand_by_station": [
            89.99,
            97.06000000000002,
            135.24444444444444,
            142.94999999999996,
            136.39166666666668,
            44.18181818181819,
            72.89444444444442
          ]
        },
        {
          "episode_name": "episode_0033.csv",
          "episode_reward": -9572.091544151306,
          "episode_length": 310,
          "vehicle_count": 310,
          "total_waiting_time": 9572.09156703949,
          "mean_waiting_time": 30.877716064453125,
          "p95_waiting_time": 158.5500030517578,
          "max_waiting_time": 180.0,
          "cv_load_imbalance": 0.6523834457012848,
          "assigned_demand_by_station": [
            2975.999999999999,
            1348.0,
            1165.55,
            771.85,
            1570.35,
            2115.650000000001,
            2382.5999999999995
          ],
          "normalized_assigned_demand_by_station": [
            297.5999999999999,
            53.92,
            64.75277777777778,
            64.32083333333334,
            130.86249999999998,
            96.16590909090914,
            132.36666666666665
          ]
        },
        {
          "episode_name": "episode_0034.csv",
          "episode_reward": -681.0,
          "episode_length": 291,
          "vehicle_count": 291,
          "total_waiting_time": 681.0,
          "mean_waiting_time": 2.3402061462402344,
          "p95_waiting_time": 13.0,
          "max_waiting_time": 19.0,
          "cv_load_imbalance": 0.3731948984461301,
          "assigned_demand_by_station": [
            1083.0,
            903.0,
            1250.0,
            983.0,
            1252.0,
            980.0,
            934.0
          ],
          "normalized_assigned_demand_by_station": [
            108.3,
            36.12,
            69.44444444444444,
            81.91666666666667,
            104.33333333333333,
            44.54545454545455,
            51.888888888888886
          ]
        },
        {
          "episode_name": "episode_0035.csv",
          "episode_reward": -584.1499994397163,
          "episode_length": 327,
          "vehicle_count": 327,
          "total_waiting_time": 584.1499994397163,
          "mean_waiting_time": 1.7863914966583252,
          "p95_waiting_time": 9.574999809265137,
          "max_waiting_time": 14.0,
          "cv_load_imbalance": 0.23801740834990967,
          "assigned_demand_by_station": [
            973.75,
            2654.7000000000003,
            1926.1499999999996,
            1451.9999999999998,
            1137.6,
            1025.9,
            1461.8999999999999
          ],
          "normalized_assigned_demand_by_station": [
            97.375,
            106.18800000000002,
            107.00833333333331,
            120.99999999999999,
            94.8,
            46.63181818181818,
            81.21666666666665
          ]
        },
        {
          "episode_name": "episode_0036.csv",
          "episode_reward": -215.0,
          "episode_length": 208,
          "vehicle_count": 208,
          "total_waiting_time": 215.0,
          "mean_waiting_time": 1.0336538553237915,
          "p95_waiting_time": 9.0,
          "max_waiting_time": 12.0,
          "cv_load_imbalance": 0.46370175321291124,
          "assigned_demand_by_station": [
            1101.0,
            1316.0,
            545.0,
            1064.0,
            1158.0,
            587.0,
            995.0
          ],
          "normalized_assigned_demand_by_station": [
            110.1,
            52.64,
            30.27777777777778,
            88.66666666666667,
            96.5,
            26.681818181818183,
            55.27777777777778
          ]
        },
        {
          "episode_name": "episode_0037.csv",
          "episode_reward": -103.79999995231628,
          "episode_length": 225,
          "vehicle_count": 225,
          "total_waiting_time": 103.79999995231628,
          "mean_waiting_time": 0.46133333444595337,
          "p95_waiting_time": 3.6399998664855957,
          "max_waiting_time": 12.0,
          "cv_load_imbalance": 0.41218293141755924,
          "assigned_demand_by_station": [
            671.0,
            2114.1000000000004,
            1643.85,
            984.85,
            890.0,
            506.20000000000005,
            442.0
          ],
          "normalized_assigned_demand_by_station": [
            67.1,
            84.56400000000002,
            91.32499999999999,
            82.07083333333334,
            74.16666666666667,
            23.00909090909091,
            24.555555555555557
          ]
        },
        {
          "episode_name": "episode_0038.csv",
          "episode_reward": -9116.0,
          "episode_length": 351,
          "vehicle_count": 351,
          "total_waiting_time": 9116.0,
          "mean_waiting_time": 25.97150993347168,
          "p95_waiting_time": 90.5,
          "max_waiting_time": 116.0,
          "cv_load_imbalance": 0.3262388646398016,
          "assigned_demand_by_station": [
            1621.0,
            2123.0,
            1647.0,
            2394.0,
            2329.0,
            2191.0,
            2325.0
          ],
          "normalized_assigned_demand_by_station": [
            162.1,
            84.92,
            91.5,
            199.5,
            194.08333333333334,
            99.5909090909091,
            129.16666666666666
          ]
        },
        {
          "episode_name": "episode_0039.csv",
          "episode_reward": -4873.683004975319,
          "episode_length": 410,
          "vehicle_count": 410,
          "total_waiting_time": 4873.683000206947,
          "mean_waiting_time": 11.887030601501465,
          "p95_waiting_time": 53.317501068115234,
          "max_waiting_time": 84.5,
          "cv_load_imbalance": 0.36560279289768566,
          "assigned_demand_by_station": [
            2799.0,
            2977.5499999999997,
            2877.45,
            1538.55,
            2242.95,
            2355.2000000000003,
            2012.2999999999997
          ],
          "normalized_assigned_demand_by_station": [
            279.9,
            119.10199999999999,
            159.85833333333332,
            128.2125,
            186.9125,
            107.05454545454546,
            111.79444444444442
          ]
        },
        {
          "episode_name": "episode_0040.csv",
          "episode_reward": -2464.1577347815037,
          "episode_length": 356,
          "vehicle_count": 356,
          "total_waiting_time": 2464.1577364206314,
          "mean_waiting_time": 6.9217915534973145,
          "p95_waiting_time": 28.950000762939453,
          "max_waiting_time": 37.0,
          "cv_load_imbalance": 0.344014525648098,
          "assigned_demand_by_station": [
            1173.05,
            2580.1,
            2499.9500000000007,
            1762.4999999999995,
            1261.65,
            834.5,
            1259.2500000000002
          ],
          "normalized_assigned_demand_by_station": [
            117.30499999999999,
            103.204,
            138.88611111111115,
            146.87499999999997,
            105.1375,
            37.93181818181818,
            69.95833333333334
          ]
        },
        {
          "episode_name": "episode_0041.csv",
          "episode_reward": -1541.799994468689,
          "episode_length": 280,
          "vehicle_count": 280,
          "total_waiting_time": 1541.799994468689,
          "mean_waiting_time": 5.5064287185668945,
          "p95_waiting_time": 36.0,
          "max_waiting_time": 54.0,
          "cv_load_imbalance": 0.3828062243311188,
          "assigned_demand_by_station": [
            1655.6000000000001,
            1993.3,
            1250.5,
            1122.35,
            841.6,
            1425.4000000000003,
            1194.25
          ],
          "normalized_assigned_demand_by_station": [
            165.56,
            79.732,
            69.47222222222223,
            93.52916666666665,
            70.13333333333334,
            64.79090909090911,
            66.34722222222223
          ]
        },
        {
          "episode_name": "episode_0042.csv",
          "episode_reward": -517.6499999761581,
          "episode_length": 207,
          "vehicle_count": 207,
          "total_waiting_time": 517.6499999761581,
          "mean_waiting_time": 2.5007247924804688,
          "p95_waiting_time": 23.700000762939453,
          "max_waiting_time": 33.0,
          "cv_load_imbalance": 0.3386298596123918,
          "assigned_demand_by_station": [
            1085.0,
            1274.6,
            1130.0,
            730.65,
            714.95,
            998.8000000000001,
            734.0
          ],
          "normalized_assigned_demand_by_station": [
            108.5,
            50.983999999999995,
            62.77777777777778,
            60.887499999999996,
            59.57916666666667,
            45.400000000000006,
            40.77777777777778
          ]
        },
        {
          "episode_name": "episode_0043.csv",
          "episode_reward": -913.0,
          "episode_length": 218,
          "vehicle_count": 218,
          "total_waiting_time": 913.0,
          "mean_waiting_time": 4.18807315826416,
          "p95_waiting_time": 34.0,
          "max_waiting_time": 44.0,
          "cv_load_imbalance": 0.4452021228158923,
          "assigned_demand_by_station": [
            1346.0,
            1322.0,
            830.0,
            929.0,
            964.0,
            950.0,
            814.0
          ],
          "normalized_assigned_demand_by_station": [
            134.6,
            52.88,
            46.111111111111114,
            77.41666666666667,
            80.33333333333333,
            43.18181818181818,
            45.22222222222222
          ]
        },
        {
          "episode_name": "episode_0044.csv",
          "episode_reward": -4815.0,
          "episode_length": 304,
          "vehicle_count": 304,
          "total_waiting_time": 4815.0,
          "mean_waiting_time": 15.838815689086914,
          "p95_waiting_time": 58.849998474121094,
          "max_waiting_time": 72.0,
          "cv_load_imbalance": 0.30745462732366813,
          "assigned_demand_by_station": [
            1289.0,
            1378.0,
            1176.0,
            1575.0,
            1452.0,
            1649.0,
            1644.0
          ],
          "normalized_assigned_demand_by_station": [
            128.9,
            55.12,
            65.33333333333333,
            131.25,
            121.0,
            74.95454545454545,
            91.33333333333333
          ]
        },
        {
          "episode_name": "episode_0045.csv",
          "episode_reward": -12110.915291786194,
          "episode_length": 441,
          "vehicle_count": 441,
          "total_waiting_time": 12110.915305614471,
          "mean_waiting_time": 27.46239471435547,
          "p95_waiting_time": 116.6326904296875,
          "max_waiting_time": 131.25,
          "cv_load_imbalance": 0.5971609894114672,
          "assigned_demand_by_station": [
            2850.5,
            3386.15,
            1154.6000000000001,
            934.5500000000002,
            950.1999999999997,
            1555.3999999999996,
            3701.6
          ],
          "normalized_assigned_demand_by_station": [
            285.05,
            135.446,
            64.14444444444445,
            77.87916666666668,
            79.18333333333331,
            70.69999999999999,
            205.64444444444445
          ]
        },
        {
          "episode_name": "episode_0046.csv",
          "episode_reward": -1058.0,
          "episode_length": 257,
          "vehicle_count": 257,
          "total_waiting_time": 1058.0,
          "mean_waiting_time": 4.116731643676758,
          "p95_waiting_time": 29.0,
          "max_waiting_time": 60.0,
          "cv_load_imbalance": 0.42377176689201757,
          "assigned_demand_by_station": [
            1514.0,
            1628.0,
            1076.0,
            1072.0,
            1049.0,
            924.0,
            1030.0
          ],
          "normalized_assigned_demand_by_station": [
            151.4,
            65.12,
            59.77777777777778,
            89.33333333333333,
            87.41666666666667,
            42.0,
            57.22222222222222
          ]
        },
        {
          "episode_name": "episode_0047.csv",
          "episode_reward": -77.0,
          "episode_length": 272,
          "vehicle_count": 272,
          "total_waiting_time": 77.0,
          "mean_waiting_time": 0.28308823704719543,
          "p95_waiting_time": 2.0,
          "max_waiting_time": 10.0,
          "cv_load_imbalance": 0.372003562382206,
          "assigned_demand_by_station": [
            809.6,
            2686.1,
            1850.6000000000001,
            1172.1,
            1034.0,
            623.0999999999999,
            723.5
          ],
          "normalized_assigned_demand_by_station": [
            80.96000000000001,
            107.444,
            102.81111111111112,
            97.675,
            86.16666666666667,
            28.322727272727267,
            40.19444444444444
          ]
        },
        {
          "episode_name": "episode_0048.csv",
          "episode_reward": -288.0,
          "episode_length": 145,
          "vehicle_count": 145,
          "total_waiting_time": 288.0,
          "mean_waiting_time": 1.9862068891525269,
          "p95_waiting_time": 16.0,
          "max_waiting_time": 21.0,
          "cv_load_imbalance": 0.5438442031117109,
          "assigned_demand_by_station": [
            1057.0,
            505.0,
            684.0,
            760.0,
            748.0,
            743.0,
            503.0
          ],
          "normalized_assigned_demand_by_station": [
            105.7,
            20.2,
            38.0,
            63.333333333333336,
            62.333333333333336,
            33.77272727272727,
            27.944444444444443
          ]
        },
        {
          "episode_name": "episode_0049.csv",
          "episode_reward": -3344.7000002861023,
          "episode_length": 374,
          "vehicle_count": 374,
          "total_waiting_time": 3344.7000002861023,
          "mean_waiting_time": 8.943047523498535,
          "p95_waiting_time": 43.0,
          "max_waiting_time": 51.0,
          "cv_load_imbalance": 0.29202253259425603,
          "assigned_demand_by_station": [
            1275.0,
            1759.15,
            1475.85,
            1235.0,
            1425.0,
            1370.0,
            1026.0
          ],
          "normalized_assigned_demand_by_station": [
            127.5,
            70.366,
            81.99166666666666,
            102.91666666666667,
            118.75,
            62.27272727272727,
            57.0
          ]
        }
      ],
      "mean_load_imbalance": 0.47637541520181886
    }
  ]
}